{
  "type": "createmissiles:nbt_crafting_shaped",
  "category": "misc",
  "key": {
    "@": {
      "item": "createmissiles:warhead_assembly",
      "nbt": "{PartType:\"createmissiles:firework_warhead\"}"
    },
    "#": {
      "item": "minecraft:anvil"
    },
    "F": {
      "item": "createmissiles:firework_upgrade_core"
    }
  },
  "pattern": [
    "#@#",
    "@F@",
    "#@#"
  ],
  "result": {
    "item": "createmissiles:warhead_assembly",
    "nbt": "{PartType:\"createmissiles:direct_hit_warhead\"}"
  }
}