{
  "type": "create:mechanical_crafting",
  "acceptMirrored": false,
  "key": {
    "B": {
      "item": "create:brass_sheet"
    },
    "P": {
      "item": "create:precision_mechanism"
    },
    "C": {
      "item": "minecraft:compass"
    },
    "T": {
      "item": "minecraft:tinted_glass"
    },
    "F": {
      "item": "create:brass_casing"
    }
  },
  "pattern": [
    "BTB",
    "BCB",
    " F ",
    "BPB"
  ],
  "result": {
    "count": 1,
    "item": "createmissiles:navigation_panel"
  }
}